{"page": "profile", "navbar": {"title": "Statdive", "logo": null, "search_bar": {"type": "select", "searches": [{"label": "players", "url": "/players/search/", "type": "fetch"}, {"label": "teams", "url": "/teams/data/team_list/", "type": "load"}]}, "resources": {"type": "sections", "component": "a", "title": "Resources", "items": {"Rumors": [{"label": "HoopsHype", "props": {"target": "_blank", "href": "http://hoopshype.com"}}, {"label": "HoopRumors", "props": {"target": "_blank", "href": "https://www.hoopsrumors.com"}}], "Draft": [{"label": "Espn Draft News", "props": {"target": "_blank", "href": "http://www.espn.com/nba/draft/news"}}, {"label": "Draft Express", "props": {"target": "_blank", "href": "http://www.draftexpress.com"}}, {"label": "NBADraft.net", "props": {"target": "_blank", "href": "http://www.nbadraft.net"}}], "Salary": [{"label": "ESPN Trade Machine", "props": {"target": "_blank", "href": "http://www.espn.com/nba/tradeMachine"}}, {"label": "Spotrac", "props": {"target": "_blank", "href": "http://www.spotrac.com/nba/"}}]}}, "side_nav": [{"primary": "Stats", "props": {"href": "/stats/"}}, {"primary": "Standings", "props": {"href": "/seasons/standings/2018/"}}, {"primary": "Draft", "props": {"href": "/draft/"}}]}, "header": {"heading": "NBA Draft"}, "tabs": [{"label": "Prospects", "type": "datatable", "url": "/draft/data/history/2018/", "args": {"ordering": ["GP", "GS", "MIN", "FG", "FGA", "FG%", "3P", "3PA", "3P%", "FT", "FTA", "FT%", "ORB", "DRB", "REB", "AST", "STL", "BLK", "TOV", "PF", "PTS"], "renders": {"GP": {"decimal_places": 0, "type": "number"}, "GS": {"decimal_places": 0, "type": "number"}, "MIN": {"decimal_places": 0, "type": "number"}, "FG": {"decimal_places": 0, "type": "number"}, "FGA": {"decimal_places": 0, "type": "number"}, "FG%": {"decimal_places": 1, "type": "percent"}, "3P": {"decimal_places": 0, "type": "number"}, "3PA": {"decimal_places": 0, "type": "number"}, "3P%": {"decimal_places": 1, "type": "percent"}, "FT": {"decimal_places": 0, "type": "number"}, "FTA": {"decimal_places": 0, "type": "number"}, "FT%": {"decimal_places": 1, "type": "percent"}, "ORB": {"decimal_places": 0, "type": "number"}, "DRB": {"decimal_places": 0, "type": "number"}, "REB": {"decimal_places": 0, "type": "number"}, "AST": {"decimal_places": 0, "type": "number"}, "STL": {"decimal_places": 0, "type": "number"}, "BLK": {"decimal_places": 0, "type": "number"}, "TOV": {"decimal_places": 0, "type": "number"}, "PF": {"decimal_places": 0, "type": "number"}, "PTS": {"decimal_places": 0, "type": "number"}}, "labels": {}, "calculations": {"FG%": {"calc": "ratio", "num": "FG", "dom": "FGA"}, "3P%": {"calc": "ratio", "num": "3P", "dom": "3PA"}, "FT%": {"calc": "ratio", "num": "FT", "dom": "FTA"}}, "head": {"PTS": {"title": "points"}, "REB": {"title": "rebounds"}, "AST": {"title": "assists"}, "BLK": {"title": "blocks"}, "STL": {"title": "steals"}, "TOV": {"title": "turnovers"}, "FG": {"title": "field goals"}, "FGA": {"title": "fields goal attempts"}, "3P": {"title": "3-pointers"}, "3PA": {"title": "3-point attempts"}, "FT": {"title": "free throws"}, "FTA": {"title": "free throw attempts"}, "MIN": {"title": "minutes"}, "PF": {"title": "personal fouls"}, "ORB": {"title": "Offensive Rebounds"}, "DRB": {"title": "Defensive Rebounds"}, "GS": {"title": "games started"}, "GP": {"title": "games played"}, "FG%": {"title": "field goal percentage"}, "3P%": {"title": "three point percentage"}, "FT%": {"title": "free throw percentage"}}, "data": []}}, {"label": "History", "type": "datatable", "url": "/draft/data/history/2018/", "args": {"ordering": ["round", "pick", "team", "player", "position", "age", "college", "height", "weight", "standing_reach", "wingspan", "max_vertical"], "column_labels": ["round", "pick", "team", "player"], "freeze": ["round", "pick", "team", "player"], "sortColumn": "pick", "sortDir": -1, "renders": {"team": {"type": "html", "element": "a", "text": "{{ row.team_id }}", "attrs": {"href": "{{ row.team_url }}"}, "reference": "team_id"}, "player": {"type": "html", "element": "a", "text": "{{ row.player_name }}", "attrs": {"href": "{{ row.player_url }}"}, "reference": "player_name"}}, "labels": {"round": "Round", "pick": "Pick", "team": "Team", "player": "Player", "position": "Position", "age": "Age", "college": "College", "height": "Height", "weight": "Weight", "standing_reach": "Standing Reach", "wingspan": "Wingspan", "max_vertical": "Max Vertical"}, "calculations": {}, "head": {}, "data": []}}], "quick_menu": {"label": "Year", "options": [{"label": 2017, "href": "/draft/2017/"}, {"label": 2016, "href": "/draft/2016/"}, {"label": 2015, "href": "/draft/2015/"}, {"label": 2014, "href": "/draft/2014/"}, {"label": 2013, "href": "/draft/2013/"}, {"label": 2012, "href": "/draft/2012/"}, {"label": 2011, "href": "/draft/2011/"}, {"label": 2010, "href": "/draft/2010/"}, {"label": 2009, "href": "/draft/2009/"}, {"label": 2008, "href": "/draft/2008/"}, {"label": 2007, "href": "/draft/2007/"}, {"label": 2006, "href": "/draft/2006/"}, {"label": 2005, "href": "/draft/2005/"}, {"label": 2004, "href": "/draft/2004/"}, {"label": 2003, "href": "/draft/2003/"}, {"label": 2002, "href": "/draft/2002/"}, {"label": 2001, "href": "/draft/2001/"}, {"label": 2000, "href": "/draft/2000/"}, {"label": 1999, "href": "/draft/1999/"}, {"label": 1998, "href": "/draft/1998/"}, {"label": 1997, "href": "/draft/1997/"}, {"label": 1996, "href": "/draft/1996/"}, {"label": 1995, "href": "/draft/1995/"}, {"label": 1994, "href": "/draft/1994/"}, {"label": 1993, "href": "/draft/1993/"}, {"label": 1992, "href": "/draft/1992/"}, {"label": 1991, "href": "/draft/1991/"}, {"label": 1990, "href": "/draft/1990/"}, {"label": 1989, "href": "/draft/1989/"}, {"label": 1988, "href": "/draft/1988/"}, {"label": 1987, "href": "/draft/1987/"}, {"label": 1986, "href": "/draft/1986/"}, {"label": 1985, "href": "/draft/1985/"}, {"label": 1984, "href": "/draft/1984/"}, {"label": 1983, "href": "/draft/1983/"}, {"label": 1982, "href": "/draft/1982/"}, {"label": 1981, "href": "/draft/1981/"}, {"label": 1980, "href": "/draft/1980/"}, {"label": 1979, "href": "/draft/1979/"}, {"label": 1978, "href": "/draft/1978/"}, {"label": 1977, "href": "/draft/1977/"}, {"label": 1976, "href": "/draft/1976/"}, {"label": 1975, "href": "/draft/1975/"}, {"label": 1974, "href": "/draft/1974/"}, {"label": 1973, "href": "/draft/1973/"}, {"label": 1972, "href": "/draft/1972/"}, {"label": 1971, "href": "/draft/1971/"}, {"label": 1970, "href": "/draft/1970/"}, {"label": 1969, "href": "/draft/1969/"}], "value": 2018}}